uiautomationtools/__init__.py
uiautomationtools/helpers/__init__.py
uiautomationtools/helpers/decorator_helpers.py
uiautomationtools/helpers/dictionary_helpers.py
uiautomationtools/helpers/directory_helpers.py
uiautomationtools/helpers/json_helpers.py
uiautomationtools/helpers/list_helpers.py
uiautomationtools/helpers/string_helpers.py
uiautomationtools/logging/__init__.py
uiautomationtools/logging/logger.py
uiautomationtools/models/__init__.py
uiautomationtools/models/model_conversion.py
uiautomationtools/proxy/__init__.py
uiautomationtools/proxy/proxy.py
uiautomationtools/pytest/__init__.py
uiautomationtools/pytest/selenium_pytest.py
uiautomationtools/selenium/__init__.py
uiautomationtools/selenium/selenium_appium_shared.py
uiautomationtools/selenium/appium/__init__.py
uiautomationtools/selenium/appium/appium_android.py
uiautomationtools/selenium/appium/appium_factory.py
uiautomationtools/selenium/appium/appium_ios.py
uiautomationtools/selenium/appium/appium_shared.py
uiautomationtools/selenium/selenium/__init__.py
uiautomationtools/selenium/selenium/selenium_extended.py
uiautomationtools/selenium/selenium/selenium_remote.py
uiautomationtools/validations/__init__.py
uiautomationtools/validations/validations.py
ui_automation_tools_mbt-1.3.1.dist-info/LICENSE.txt
ui_automation_tools_mbt-1.3.1.dist-info/METADATA
ui_automation_tools_mbt-1.3.1.dist-info/WHEEL
ui_automation_tools_mbt-1.3.1.dist-info/top_level.txt
ui_automation_tools_mbt-1.3.1.dist-info/RECORD
