Metadata-Version: 2.1
Name: ui-automation-tools-mbt
Version: 1.3.1
Summary: Tools for UI automation using model based testing
Home-page: https://github.com/rakutentech/ui-automation-tools-mbt
Author: Ashton Szabo
Author-email: ashton.szabo@rakuten.com
License: UNKNOWN
Platform: UNKNOWN
Classifier: Programming Language :: Python :: 3
Classifier: License :: OSI Approved :: MIT License
Classifier: Operating System :: OS Independent
Requires-Python: >=3.8
License-File: LICENSE.txt
Requires-Dist: pytest
Requires-Dist: pytest-xdist
Requires-Dist: pytest-parallel
Requires-Dist: altwalker
Requires-Dist: selenium (<4.0.0)
Requires-Dist: Appium-Python-Client
Requires-Dist: numpy
Requires-Dist: langdetect
Requires-Dist: lxml
Requires-Dist: bs4
Requires-Dist: pyautogui
Requires-Dist: pyperclip
Requires-Dist: pypeln
Requires-Dist: mitmproxy
